{
	"class" : {
		"canBeRoot" : "tcj 10/7/2018 16:09",
		"description" : "tcj 10/7/2018 16:10",
		"initialize" : "tcj 10/7/2018 16:12" },
	"instance" : {
		"directory" : "tcj 10/7/2018 15:56",
		"directory:" : "tcj 10/7/2018 15:56",
		"directoryName" : "tcj 10/7/2018 16:06",
		"directoryName:" : "tcj 10/7/2018 16:06",
		"getSVGFileNames" : "tcj 10/7/2018 16:04",
		"initialize" : "tcj 10/7/2018 16:06",
		"renderContentOn:" : "tcj 10/7/2018 16:08",
		"server" : "tcj 10/7/2018 15:56",
		"server:" : "tcj 10/7/2018 15:56",
		"svgFileNames" : "tcj 10/7/2018 16:06",
		"svgFileNames:" : "tcj 10/7/2018 16:06" } }
