{
	"class" : {
		 },
	"instance" : {
		"allTextsForCurrentStatus" : "tcj 12/12/2018 23:42",
		"blurbForId:" : "tcj 12/13/2018 00:14",
		"blurbRegistry" : "tcj 4/13/2019 22:05",
		"blurbRegistry:" : "tcj 10/8/2018 12:43",
		"browsingBlurb" : "tcj 12/12/2018 23:26",
		"browsingBlurb:" : "tcj 12/12/2018 23:26",
		"browsingClipart" : "tcj 12/13/2018 00:17",
		"browsingClipart:" : "tcj 12/12/2018 23:26",
		"browsingText" : "tcj 12/12/2018 23:26",
		"browsingText:" : "tcj 12/12/2018 23:26",
		"clipartForBrowser" : "tcj 10/21/2018 23:04",
		"clipartForId:" : "tcj 12/13/2018 00:15",
		"clipartRegistry" : "tcj 4/13/2019 22:06",
		"clipartRegistry:" : "tcj 10/7/2018 17:09",
		"currentActivity" : "tcj 10/21/2018 17:41",
		"currentActivity:" : "tcj 10/21/2018 17:41",
		"currentBlurb" : "tcj 4/6/2019 18:27",
		"currentBlurb:" : "tcj 4/6/2019 18:27",
		"currentText" : "tcj 12/12/2018 23:19",
		"currentText:" : "tcj 12/12/2018 23:19",
		"currentTextBlurb" : "tcj 4/1/2019 21:36",
		"initialize" : "tcj 4/13/2019 22:06",
		"makeActive:" : "tcj 10/21/2018 18:17",
		"newRandomBlurb" : "tcj 12/12/2018 23:38",
		"newRandomClipart" : "tcj 12/12/2018 23:38",
		"newRandomText" : "tcj 12/12/2018 23:39",
		"randomBlurb" : "tcj 10/8/2018 12:43",
		"randomClipart" : "tcj 10/7/2018 21:09",
		"randomSvgUrl" : "tcj 10/7/2018 22:43",
		"saveAndNew" : "tcj 12/12/2018 23:22",
		"saveCurrentText" : "tcj 12/12/2018 23:21",
		"switchToBrowsing" : "tcj 10/21/2018 18:25",
		"switchToTextEntry" : "tcj 10/21/2018 18:25",
		"textBlurb" : "tcj 12/12/2018 23:53",
		"textClipart" : "tcj 12/13/2018 00:05",
		"textClipartUrl" : "tcj 12/13/2018 00:40",
		"textsForAllUsers" : "tcj 10/21/2018 17:35",
		"textsForBrowsing" : "tcj 12/12/2018 23:43",
		"textsForCurrentUser" : "tcj 12/12/2018 23:43",
		"timeStamp" : "tcj 4/6/2019 18:27",
		"timeStamp:" : "tcj 4/6/2019 18:27",
		"urlForClipartFile:" : "tcj 12/13/2018 00:40",
		"user" : "tcj 10/7/2018 17:09",
		"user:" : "tcj 10/7/2018 17:09",
		"userId" : "tcj 12/12/2018 08:23" } }
